parspin/__init__.py
parspin/burt.py
parspin/partitions.py
parspin/plotting.py
parspin/simnulls.py
parspin/spatial.py
parspin/surface.py
parspin/surrogates.py
parspin/utils.py
parspin-0.0.1.dist-info/LICENSE
parspin-0.0.1.dist-info/METADATA
parspin-0.0.1.dist-info/WHEEL
parspin-0.0.1.dist-info/top_level.txt
parspin-0.0.1.dist-info/RECORD
